{
  "has_precipitation": false,
  "temperature": 0.5,
  "downfall": 0.0,
  "effects": {
    "sky_color": 8026756,
    "fog_color": 7036269,
    "water_color": 6250335,
    "water_fog_color": 5272890,
    "grass_color": 9936229,
    "foliage_color": 9936229,
    "mood_sound": {
      "sound": "minecraft:ambient.cave",
      "tick_delay": 6000,
      "block_search_extent": 8,
      "offset": 2.0
    }
  },
  "carvers": {
    "air": [
      "astrogreg:pluto_cave",
      "astrogreg:pluto_cave_extra"
    ]
  },
  "features": [
    [],
    [
      "astrogreg:pluto_boulder",
      "astrogreg:topaz_geode",
      "astrogreg:pluto_boulder_mycelite"
    ],
    [], [], [],
    [
      "astrogreg:plutonian_shrub",
      "astrogreg:scorch_grass_patch",
      "astrogreg:dead_bush"
    ],
    [],
    [
      "astrogreg:aeronos_mushroom_configured_sparse",
      "astrogreg:strophar_mushroom_configured_sparse",
      "astrogreg:strophar_mushroom_large_configured_sparse"
    ],
    [], [],
    ["astrogreg:solite_columns"]
  ],
  "spawners": {
    "creature": [
      {
        "type": "ad_astra:glacian_ram",
        "weight": 5,
        "minCount": 1,
        "maxCount": 3
      },
      {
        "type": "astrogreg:glaciodillo",
        "weight": 2,
        "minCount": 1,
        "maxCount": 2
      }
    ],
    "monster": [
      {
        "type": "astrogreg:spig",
        "weight": 15,
        "minCount": 2,
        "maxCount": 4
      }
    ],
    "ambient": [],
    "water_creature": [],
    "underground_water_creature": [],
    "water_ambient": [],
    "misc": []
  },
  "spawn_costs": {}
}
